{
    "obj_to_poseid": {
        "GarbageCan|2|3": [
            "2.0_1.5_0.0_0_True",
            "2.0_0.5_0.0_0_True",
            "2.0_3.0_270.0_0_True",
            "0.75_3.0_0.0_0_True",
            "1.75_4.0_270.0_0_True",
            "2.25_1.5_0.0_0_True",
            "3.0_0.75_0.0_0_True",
            "3.0_1.25_0.0_0_True"
        ],
        "door|1|2": [
            "2.0_1.5_0.0_0_True",
            "2.0_0.5_0.0_0_True",
            "0.5_3.0_90.0_0_True",
            "3.0_2.25_0.0_0_True",
            "2.25_1.5_0.0_0_True",
            "3.0_0.75_0.0_0_True",
            "2.0_3.0_90.0_0_True",
            "3.0_2.25_0.0_0_True",
            "3.0_1.25_0.0_0_True",
            "2.0_3.0_90.0_0_True"
        ],
        "window|2|1": [
            "2.0_1.5_0.0_0_True",
            "2.0_0.5_0.0_0_True",
            "0.5_3.0_90.0_0_True",
            "1.75_3.75_0.0_0_True",
            "0.75_3.0_0.0_0_True",
            "3.0_2.25_0.0_0_True",
            "2.25_1.5_0.0_0_True",
            "3.0_0.75_0.0_0_True",
            "3.0_2.25_0.0_0_True",
            "3.0_1.25_0.0_0_True"
        ],
        "wall|2|3.24|0.00|3.24|4.86": [
            "2.0_1.5_0.0_0_True",
            "2.0_0.5_0.0_0_True",
            "0.5_3.0_90.0_0_True",
            "2.0_3.0_180.0_0_True",
            "1.0_3.0_180.0_0_True",
            "2.0_2.0_180.0_0_True",
            "2.0_1.5_90.0_0_True",
            "2.0_0.5_90.0_0_True",
            "3.0_1.75_180.0_0_True",
            "3.0_0.75_180.0_0_True",
            "1.5_0.5_90.0_0_True",
            "2.0_1.5_180.0_0_True",
            "3.0_2.25_0.0_0_True",
            "2.25_1.5_0.0_0_True",
            "3.0_0.75_0.0_0_True",
            "2.0_3.0_90.0_0_True",
            "2.0_2.0_90.0_0_True",
            "3.0_2.75_90.0_0_True",
            "3.0_1.75_90.0_0_True",
            "2.5_3.0_180.0_0_True",
            "3.0_2.0_180.0_0_True",
            "3.0_2.25_0.0_0_True",
            "3.0_1.25_0.0_0_True",
            "2.0_3.0_90.0_0_True",
            "3.0_2.75_90.0_0_True",
            "3.0_1.75_90.0_0_True",
            "3.0_3.0_180.0_0_True"
        ],
        "room|2": [
            "2.0_1.5_0.0_0_True",
            "2.0_0.5_0.0_0_True",
            "0.5_3.0_90.0_0_True",
            "2.0_3.0_180.0_0_True",
            "1.0_3.0_180.0_0_True",
            "2.0_2.0_180.0_0_True",
            "0.25_2.25_180.0_0_True",
            "2.0_3.0_270.0_0_True",
            "2.0_2.0_270.0_0_True",
            "2.0_1.0_270.0_0_True",
            "3.0_1.75_180.0_0_True",
            "3.0_1.25_270.0_0_True",
            "0.75_3.0_0.0_0_True",
            "1.75_4.0_270.0_0_True",
            "1.5_0.5_90.0_0_True",
            "2.0_1.0_270.0_0_True",
            "3.0_0.75_270.0_0_True",
            "3.0_2.25_0.0_0_True",
            "2.25_1.5_0.0_0_True",
            "3.0_0.75_0.0_0_True",
            "2.5_3.0_180.0_0_True",
            "3.0_2.0_180.0_0_True",
            "3.0_2.25_0.0_0_True",
            "3.0_1.25_0.0_0_True",
            "3.0_3.0_180.0_0_True"
        ],
        "wall|2|0.00|0.00|0.00|4.86": [
            "2.0_1.5_0.0_0_True",
            "2.0_0.5_0.0_0_True",
            "2.0_3.0_180.0_0_True",
            "1.0_3.0_180.0_0_True",
            "0.25_2.25_180.0_0_True",
            "2.0_3.0_270.0_0_True",
            "1.0_3.0_270.0_0_True",
            "2.0_2.0_270.0_0_True",
            "2.0_1.0_270.0_0_True",
            "3.0_1.25_270.0_0_True",
            "0.75_3.0_0.0_0_True",
            "0.75_4.0_0.0_0_True",
            "1.75_4.0_270.0_0_True",
            "0.75_4.0_270.0_0_True",
            "2.0_1.0_270.0_0_True",
            "3.0_0.75_270.0_0_True",
            "2.25_1.5_0.0_0_True",
            "3.0_0.75_0.0_0_True",
            "2.5_3.0_180.0_0_True",
            "3.0_1.25_0.0_0_True"
        ],
        "Ceiling_room|2|0|3.599298|0": [
            "2.0_1.5_0.0_0_True",
            "2.0_0.5_0.0_0_True",
            "0.5_3.0_90.0_0_True",
            "2.0_3.0_180.0_0_True",
            "1.0_3.0_180.0_0_True",
            "0.25_2.25_180.0_0_True",
            "3.0_1.25_270.0_0_True",
            "3.0_0.75_270.0_0_True",
            "3.0_2.25_0.0_0_True",
            "2.25_1.5_0.0_0_True",
            "3.0_0.75_0.0_0_True",
            "2.5_3.0_180.0_0_True",
            "3.0_2.25_0.0_0_True",
            "3.0_1.25_0.0_0_True",
            "3.0_3.0_180.0_0_True"
        ],
        "window|2|0": [
            "2.0_1.5_0.0_0_True",
            "2.0_0.5_0.0_0_True",
            "2.0_3.0_270.0_0_True",
            "1.0_3.0_270.0_0_True",
            "2.0_2.0_270.0_0_True",
            "2.0_1.0_270.0_0_True",
            "3.0_1.25_270.0_0_True",
            "0.75_3.0_0.0_0_True",
            "1.75_4.0_270.0_0_True",
            "0.75_4.0_270.0_0_True",
            "2.0_1.0_270.0_0_True",
            "3.0_0.75_270.0_0_True",
            "2.25_1.5_0.0_0_True",
            "3.0_0.75_0.0_0_True",
            "3.0_1.25_0.0_0_True"
        ],
        "wall|2|0.00|4.86|3.24|4.86": [
            "2.0_1.5_0.0_0_True",
            "2.0_0.5_0.0_0_True",
            "0.5_3.0_90.0_0_True",
            "2.0_3.0_270.0_0_True",
            "1.75_3.75_0.0_0_True",
            "0.75_3.0_0.0_0_True",
            "0.75_4.0_0.0_0_True",
            "1.75_4.0_270.0_0_True",
            "3.0_2.25_0.0_0_True",
            "2.25_1.5_0.0_0_True",
            "3.0_0.75_0.0_0_True",
            "3.0_2.25_0.0_0_True",
            "3.0_1.25_0.0_0_True"
        ],
        "Painting|2|5": [
            "2.0_0.5_0.0_0_True",
            "0.5_3.0_90.0_0_True",
            "2.0_3.0_180.0_0_True",
            "2.0_1.5_90.0_0_True",
            "2.0_0.5_90.0_0_True",
            "1.5_0.5_90.0_0_True",
            "3.0_2.25_0.0_0_True",
            "2.25_1.5_0.0_0_True",
            "3.0_0.75_0.0_0_True",
            "2.0_3.0_90.0_0_True",
            "2.0_2.0_90.0_0_True",
            "3.0_2.75_90.0_0_True",
            "3.0_1.75_90.0_0_True",
            "2.5_3.0_180.0_0_True",
            "3.0_2.0_180.0_0_True",
            "3.0_2.25_0.0_0_True",
            "3.0_1.25_0.0_0_True",
            "2.0_3.0_90.0_0_True",
            "3.0_2.75_90.0_0_True",
            "3.0_1.75_90.0_0_True",
            "3.0_3.0_180.0_0_True"
        ],
        "Bed|2|0": [
            "2.0_0.5_0.0_0_True",
            "2.0_3.0_180.0_0_True",
            "1.0_3.0_180.0_0_True",
            "2.0_2.0_180.0_0_True",
            "2.0_1.0_180.0_0_True",
            "0.25_2.25_180.0_0_True",
            "2.0_3.0_270.0_0_True",
            "2.0_2.0_270.0_0_True",
            "2.0_1.0_270.0_0_True",
            "3.0_1.25_270.0_0_True",
            "2.0_1.5_180.0_0_True",
            "2.0_1.0_270.0_0_True",
            "3.0_0.75_270.0_0_True",
            "2.5_3.0_180.0_0_True",
            "3.0_2.0_180.0_0_True",
            "3.0_3.0_180.0_0_True"
        ],
        "Dresser|2|1___1": [
            "0.5_3.0_90.0_0_True",
            "2.0_3.0_180.0_0_True",
            "1.0_3.0_180.0_0_True",
            "2.0_2.0_180.0_0_True",
            "2.0_1.5_90.0_0_True",
            "2.0_0.5_90.0_0_True",
            "3.0_1.75_180.0_0_True",
            "1.5_0.5_90.0_0_True",
            "2.0_1.5_180.0_0_True",
            "2.5_3.0_180.0_0_True",
            "3.0_2.0_180.0_0_True",
            "3.0_3.0_180.0_0_True"
        ],
        "Dresser|2|1": [
            "0.5_3.0_90.0_0_True",
            "2.0_3.0_180.0_0_True",
            "1.0_3.0_180.0_0_True",
            "2.0_2.0_180.0_0_True",
            "2.0_1.0_180.0_0_True",
            "2.0_1.5_90.0_0_True",
            "2.0_0.5_90.0_0_True",
            "3.0_1.75_180.0_0_True",
            "1.5_0.5_90.0_0_True",
            "2.0_1.5_180.0_0_True",
            "2.5_3.0_180.0_0_True",
            "3.0_2.0_180.0_0_True",
            "3.0_3.0_180.0_0_True"
        ],
        "Dresser|2|1___2": [
            "0.5_3.0_90.0_0_True",
            "2.0_3.0_180.0_0_True",
            "1.0_3.0_180.0_0_True",
            "2.0_2.0_180.0_0_True",
            "3.0_1.75_180.0_0_True",
            "1.5_0.5_90.0_0_True",
            "2.5_3.0_180.0_0_True",
            "3.0_2.0_180.0_0_True",
            "3.0_3.0_180.0_0_True"
        ],
        "Dresser|2|1___0": [
            "0.5_3.0_90.0_0_True",
            "2.0_3.0_180.0_0_True",
            "1.0_3.0_180.0_0_True",
            "2.0_2.0_180.0_0_True",
            "2.0_1.5_90.0_0_True",
            "2.0_0.5_90.0_0_True",
            "3.0_1.75_180.0_0_True",
            "1.5_0.5_90.0_0_True",
            "2.0_1.5_180.0_0_True",
            "2.5_3.0_180.0_0_True",
            "3.0_2.0_180.0_0_True",
            "3.0_3.0_180.0_0_True"
        ],
        "BasketBall|surface|2|1": [
            "2.0_3.0_180.0_0_True",
            "1.0_3.0_180.0_0_True",
            "0.25_2.25_180.0_0_True",
            "2.0_2.0_270.0_0_True",
            "2.0_1.0_270.0_0_True",
            "3.0_1.25_270.0_0_True",
            "2.0_1.0_270.0_0_True",
            "3.0_0.75_270.0_0_True",
            "2.5_3.0_180.0_0_True"
        ],
        "TennisRacket|surface|2|2": [
            "2.0_3.0_180.0_0_True",
            "1.0_3.0_180.0_0_True",
            "0.25_2.25_180.0_0_True",
            "2.0_3.0_270.0_0_True",
            "2.0_2.0_270.0_0_True",
            "2.0_1.0_270.0_0_True",
            "3.0_1.25_270.0_0_True",
            "2.0_1.0_270.0_0_True",
            "3.0_0.75_270.0_0_True"
        ],
        "Pencil|surface|2|3": [
            "2.0_3.0_180.0_0_True",
            "1.0_3.0_180.0_0_True",
            "2.0_2.0_180.0_0_True",
            "2.0_0.5_90.0_0_True",
            "1.5_0.5_90.0_0_True",
            "2.0_1.5_180.0_0_True"
        ],
        "wall|2|0.00|0.00|3.24|0.00": [
            "2.0_3.0_180.0_0_True",
            "1.0_3.0_180.0_0_True",
            "2.0_2.0_180.0_0_True",
            "2.0_1.0_180.0_0_True",
            "0.25_2.25_180.0_0_True",
            "2.0_1.0_270.0_0_True",
            "2.0_0.5_90.0_0_True",
            "3.0_1.75_180.0_0_True",
            "3.0_0.75_180.0_0_True",
            "3.0_1.25_270.0_0_True",
            "1.5_0.5_90.0_0_True",
            "2.0_1.5_180.0_0_True",
            "2.0_0.5_180.0_0_True",
            "2.0_1.0_270.0_0_True",
            "3.0_0.75_270.0_0_True",
            "2.5_3.0_180.0_0_True",
            "3.0_2.0_180.0_0_True",
            "3.0_3.0_180.0_0_True"
        ],
        "Painting|2|4": [
            "2.0_3.0_180.0_0_True",
            "1.0_3.0_180.0_0_True",
            "2.0_2.0_180.0_0_True",
            "2.0_1.0_180.0_0_True",
            "0.25_2.25_180.0_0_True",
            "3.0_1.75_180.0_0_True",
            "3.0_1.25_270.0_0_True",
            "2.0_1.5_180.0_0_True",
            "2.0_0.5_180.0_0_True",
            "3.0_0.75_270.0_0_True",
            "2.5_3.0_180.0_0_True",
            "3.0_2.0_180.0_0_True",
            "3.0_3.0_180.0_0_True"
        ],
        "Pillow|surface|2|4": [
            "2.0_3.0_180.0_0_True",
            "1.0_3.0_180.0_0_True",
            "2.0_2.0_180.0_0_True",
            "0.25_2.25_180.0_0_True",
            "2.0_2.0_270.0_0_True",
            "2.0_1.0_270.0_0_True",
            "3.0_1.25_270.0_0_True",
            "2.0_1.5_180.0_0_True",
            "2.0_1.0_270.0_0_True",
            "3.0_0.75_270.0_0_True",
            "2.5_3.0_180.0_0_True",
            "3.0_3.0_180.0_0_True"
        ],
        "AlarmClock|surface|2|0": [
            "2.0_3.0_180.0_0_True",
            "1.0_3.0_180.0_0_True",
            "2.0_2.0_180.0_0_True",
            "2.0_0.5_90.0_0_True",
            "3.0_1.75_180.0_0_True",
            "1.5_0.5_90.0_0_True",
            "2.0_1.5_180.0_0_True",
            "2.5_3.0_180.0_0_True",
            "3.0_2.0_180.0_0_True",
            "3.0_3.0_180.0_0_True"
        ],
        "HousePlant|2|2|0": [
            "2.0_3.0_180.0_0_True",
            "1.0_3.0_180.0_0_True",
            "2.0_2.0_180.0_0_True",
            "2.0_1.0_180.0_0_True",
            "0.25_2.25_180.0_0_True",
            "3.0_1.75_180.0_0_True",
            "1.5_0.5_90.0_0_True",
            "2.0_1.5_180.0_0_True",
            "3.0_0.75_270.0_0_True",
            "2.5_3.0_180.0_0_True",
            "3.0_2.0_180.0_0_True",
            "3.0_3.0_180.0_0_True"
        ]
    },
    "ids": [
        "Bed|2|0",
        "Dresser|2|1",
        "HousePlant|2|2|0",
        "GarbageCan|2|3",
        "Painting|2|4",
        "Painting|2|5",
        "BasketBall|surface|2|1",
        "TennisRacket|surface|2|2",
        "Pillow|surface|2|4",
        "AlarmClock|surface|2|0",
        "Pencil|surface|2|3"
    ]
}